mirro/__init__.py
mirro/main.py
mirro-0.6.1.dist-info/LICENCE
mirro-0.6.1.dist-info/METADATA
mirro-0.6.1.dist-info/WHEEL
mirro-0.6.1.dist-info/entry_points.txt
mirro-0.6.1.dist-info/RECORD
