Metadata-Version: 2.1
Name: mirro
Version: 0.6.1
Summary: A safe editing wrapper: edits a temp copy, compares, and saves original backup if changed.
Home-page: https://git.sysmd.uk/guardutils/mirro
License: GPL-3.0-or-later
Author: Marco D'Aleo
Author-email: marco@marcodaleo.com
Requires-Python: >=3.10,<4.0
Classifier: License :: OSI Approved :: GNU General Public License v3 or later (GPLv3+)
Classifier: Programming Language :: Python :: 3
Classifier: Programming Language :: Python :: 3.10
Classifier: Programming Language :: Python :: 3.11
Classifier: Programming Language :: Python :: 3.12
Classifier: Programming Language :: Python :: 3.13
Requires-Dist: argcomplete (>=2)
Project-URL: Repository, https://git.sysmd.uk/guardutils/mirro
